pymaybe/__init__.py
pymaybe-0.1.6.dist-info/DESCRIPTION.rst
pymaybe-0.1.6.dist-info/METADATA
pymaybe-0.1.6.dist-info/metadata.json
pymaybe-0.1.6.dist-info/RECORD
pymaybe-0.1.6.dist-info/top_level.txt
pymaybe-0.1.6.dist-info/WHEEL
