Metadata-Version: 1.1
Name: pymaybe
Version: 0.1.6
Summary: A Python implementation of the Maybe pattern.
Home-page: https://github.com/ekampf/pymaybe
Author: Eran Kampf
Author-email: eran@ekampf.com
License: BSD
Keywords: pymaybe
Platform: UNKNOWN
Classifier: Development Status :: 5 - Production/Stable
Classifier: Intended Audience :: Developers
Classifier: License :: OSI Approved :: BSD License
Classifier: Natural Language :: English
Classifier: Programming Language :: Python :: 2
Classifier: Programming Language :: Python :: 2.5
Classifier: Programming Language :: Python :: 2.6
Classifier: Programming Language :: Python :: 2.7
Classifier: Programming Language :: Python :: 3
Classifier: Programming Language :: Python :: 3.3
Classifier: Programming Language :: Python :: 3.4
